apibean/jupyter/__init__.py
apibean/jupyter/__main__.py
apibean/jupyter/cli.py
apibean/jupyter/kernel.py
apibean/jupyter/plugins.py
apibean/jupyter/server.py
apibean/jupyter/wrapper.py
apibean_jupyter-0.1.0a4.dist-info/licenses/LICENSE
apibean_jupyter-0.1.0a4.dist-info/METADATA
apibean_jupyter-0.1.0a4.dist-info/WHEEL
apibean_jupyter-0.1.0a4.dist-info/entry_points.txt
apibean_jupyter-0.1.0a4.dist-info/top_level.txt
apibean_jupyter-0.1.0a4.dist-info/RECORD
