Metadata-Version: 2.4
Name: apibean-jupyter
Version: 0.1.0a4
Summary: Embed and manage Jupyter Server as a reusable Python component for applications and tools.
License-Expression: MIT
Requires-Python: <4.0,>=3.9
License-File: LICENSE
Requires-Dist: jupyter-server>=2.0
Requires-Dist: jupyterlab>=4.0
Dynamic: license-file
